pygomo/__init__.py
pygomo/console.py
pygomo/exceptions.py
pygomo/board/__init__.py
pygomo/board/bitboard.py
pygomo/board/interface.py
pygomo/board/renju.py
pygomo/board/zobrist.py
pygomo/client/__init__.py
pygomo/client/engine.py
pygomo/command/__init__.py
pygomo/command/hooks.py
pygomo/command/interface.py
pygomo/command/registry.py
pygomo/command/handlers/__init__.py
pygomo/command/handlers/base.py
pygomo/command/handlers/config.py
pygomo/command/handlers/game.py
pygomo/command/handlers/lifecycle.py
pygomo/command/handlers/search.py
pygomo/protocol/__init__.py
pygomo/protocol/gomocup.py
pygomo/protocol/interface.py
pygomo/protocol/models.py
pygomo/transport/__init__.py
pygomo/transport/interface.py
pygomo/transport/reader.py
pygomo/transport/subprocess.py
pygomo_lib-0.1.1.dist-info/METADATA
pygomo_lib-0.1.1.dist-info/WHEEL
pygomo_lib-0.1.1.dist-info/entry_points.txt
pygomo_lib-0.1.1.dist-info/top_level.txt
pygomo_lib-0.1.1.dist-info/RECORD
