Metadata-Version: 2.4
Name: pygomo-lib
Version: 0.1.1
Summary: A clean, extensible Python library for communicating with Gomoku engines via the Gomocup protocol.
Author: PyGomo Contributors
License: MIT License
Project-URL: Homepage, https://github.com/nguyencongminh090/pygomo
Project-URL: Repository, https://github.com/nguyencongminh090/pygomo
Project-URL: Issues, https://github.com/nguyencongminh090/pygomo/issues
Classifier: Development Status :: 3 - Alpha
Classifier: Intended Audience :: Developers
Classifier: Topic :: Games/Entertainment :: Board Games
Classifier: License :: OSI Approved :: MIT License
Classifier: Programming Language :: Python :: 3
Classifier: Programming Language :: Python :: 3.8
Classifier: Programming Language :: Python :: 3.9
Classifier: Programming Language :: Python :: 3.10
Classifier: Programming Language :: Python :: 3.11
Classifier: Programming Language :: Python :: 3.12
Classifier: Programming Language :: Python :: 3.13
Classifier: Operating System :: OS Independent
Requires-Python: >=3.8
Provides-Extra: dev
Requires-Dist: pytest>=7.0; extra == "dev"
Requires-Dist: sphinx>=7.0; extra == "dev"
Requires-Dist: furo; extra == "dev"
Requires-Dist: myst-parser; extra == "dev"
Requires-Dist: sphinx-copybutton; extra == "dev"
